[
  {
    "handle": "kevvonz",
    "name": "Kevin Hu",
    "totalCalls": 80,
    "firstCalls": 30,
    "hitRate3m": 0.375,
    "hitRate3mN": 24,
    "avgExcess3m": -0.03700098587516342,
    "generatedAt": "2026-07-14",
    "avatar": "/avatars/kevvonz.jpg"
  },
  {
    "handle": "TheProfInvestor",
    "name": "The Prof Investor",
    "totalCalls": 2033,
    "firstCalls": 304,
    "hitRate3m": 0.47767857142857145,
    "hitRate3mN": 224,
    "avgExcess3m": 0.1087908273396632,
    "generatedAt": "2026-07-15",
    "avatar": "/avatars/TheProfInvestor.jpg"
  },
  {
    "handle": "thelonginvest",
    "name": "The Long Invest",
    "totalCalls": 2392,
    "firstCalls": 125,
    "hitRate3m": 0.41237113402061853,
    "hitRate3mN": 97,
    "avgExcess3m": 0.016478210699139635,
    "generatedAt": "2026-07-15",
    "avatar": "/avatars/thelonginvest.jpg"
  },
  {
    "handle": "roadto100kportfolio",
    "name": "@roadto100kportfolio",
    "totalCalls": 240,
    "firstCalls": 76,
    "hitRate3m": 0.5555555555555556,
    "hitRate3mN": 45,
    "avgExcess3m": 0.07346250638277807,
    "generatedAt": "2026-07-14",
    "avatar": "/avatars/roadto100kportfolio.jpg"
  },
  {
    "handle": "johnnylixf",
    "name": "Johnny Li",
    "totalCalls": 159,
    "firstCalls": 78,
    "hitRate3m": 0.4666666666666667,
    "hitRate3mN": 45,
    "avgExcess3m": 0.07160273446167807,
    "generatedAt": "2026-07-14",
    "avatar": "/avatars/johnnylixf.jpg"
  }
]